metabase_query_api/__init__.py
metabase_query_api/async_card.py
metabase_query_api/async_dataset.py
metabase_query_api/async_query.py
metabase_query_api/retry_errors.py
metabase_query_api/sync_card.py
metabase_query_api/sync_dataset.py
metabase_query_api/sync_query.py
metabase_query_api-1.1.3.dist-info/LICENSE
metabase_query_api-1.1.3.dist-info/METADATA
metabase_query_api-1.1.3.dist-info/WHEEL
metabase_query_api-1.1.3.dist-info/top_level.txt
metabase_query_api-1.1.3.dist-info/RECORD
