Metadata-Version: 2.1
Name: metabase-query-api
Version: 1.1.3
Summary: Metabase Query API with Retry and Bulk Param Values
Home-page: https://github.com/tranngocminhhieu/metabase-query-api
Author: Tran Ngoc Minh Hieu
Author-email: tnmhieu@gmail.com
License-File: LICENSE
Requires-Dist: requests
Requires-Dist: tenacity
Requires-Dist: nest-asyncio
